rtl/single.v
module pc(
  input             clk,
  input             rst,
  input       [4:0] in,
  output reg  [4:0] out
);
  always @(posedge clk) begin
    if (rst) out <= 5'b0;
    else out <= in;
  end
endmodule

module acc(
  input             clk,
  input             rst,
  input             ld,
  input       [7:0] in,
  output reg  [7:0] out
);
  always @(posedge clk) begin
    if (rst) out = 8'b0;
    else if (ld) out <= in;
  end
endmodule

module alu(
  input       [2:0] op,
  input       [7:0] a,
  input       [7:0] b,
  output reg  [7:0] out
);
  always @* begin
    case(op)
      3'b000: out = a + b;
      3'b001: out = a - b;
      3'b010: out = a & b;
      3'b011: out = a | b;
      3'b100: out = ~ b;
      3'b101: out = a ^ b;
      3'b110: out = a ~^ b;
      default:out = 8'b0;
    endcase
  end
endmodule

module adder(
  input   [4:0] a,
  input   [4:0] b,
  output  [4:0] out
);
  assign out = a + b;
endmodule

module mux2to1#(
  parameter BITS = 8
)(
  input               sel,
  input   [BITS-1:0]  in1,
  input   [BITS-1:0]  in2,
  output  [BITS-1:0]  out
);
  assign out = sel ? in2 : in1;
endmodule

module controller(
  input  [2:0]  op,
  output reg    rd_mem,
  output reg    wr_mem,
  output reg    ld_ac,
  output reg    ac_src,
  output reg    pc_src,
  output reg    branch
);
  always @* begin
    rd_mem = 1'b0;
    wr_mem = 1'b0;
    ld_ac  = 1'b0;
    ac_src = 1'b0;
    pc_src = 1'b0;
    branch = 1'b0;
    case(op)
      3'b000: begin // LDA [addr]
        rd_mem = 1'b1;
        wr_mem = 1'b0;
        ld_ac  = 1'b1;
        ac_src = 1'b0;
      end
      3'b001: begin // SUB [addr]
        rd_mem = 1'b1;
        wr_mem = 1'b0;
        ld_ac  = 1'b1;
        ac_src = 1'b0;
      end
      3'b010: begin // AND [addr]
        rd_mem = 1'b1;
        wr_mem = 1'b0;
        ld_ac  = 1'b1;
        ac_src = 1'b0;
      end
      3'b011: begin // ORA [addr]
        rd_mem = 1'b1;
        wr_mem = 1'b0;
        ld_ac  = 1'b1;
        ac_src = 1'b0;
      end
      3'b100: begin // NOT
        rd_mem = 1'b1;
        wr_mem = 1'b0;
        ld_ac  = 1'b1;
        ac_src = 1'b0;
      end
      3'b101: begin // XOR [addr]
        rd_mem = 1'b1;
        wr_mem = 1'b0;
        ld_ac  = 1'b1;
        ac_src = 1'b0;
      end
      3'b110: begin // XNOR [addr]
        rd_mem = 1'b1;
        wr_mem = 1'b0;
        ld_ac  = 1'b1;
        ac_src = 1'b0;
      end
      3'b111: begin // JMP [addr]
        rd_mem = 1'b0;
        wr_mem = 1'b0;
        ld_ac  = 1'b0;
        ac_src = 1'b0;
        pc_src = 1'b1;
        branch = 1'b1;
      end
      default: begin
        rd_mem = 1'b0;
        wr_mem = 1'b0;
        ld_ac  = 1'b0;
        ac_src = 1'b0;
        pc_src = 1'b0;   
      end
    endcase
  end
endmodule

module datamem(
  input             rd,
  input             wr,
  input       [4:0] addr,
  input       [7:0] in,
  output reg  [7:0] out
);
  reg         [7:0] mem[0:31];
  always @(rd, addr)  if (rd) out = mem[addr];
  always @(wr, in)    if (wr) mem[addr] = in;
  initial begin
    mem[0] = 8'd1;
    mem[1] = 8'd2;
    mem[2] = 8'd3;
    mem[3] = 8'd4;
    mem[4] = 8'd5;
  end
endmodule

module codemem(
  input       [4:0] addr,
  output reg  [7:0] out
);
  reg         [7:0] ins[0:31];
  always @(addr) out = ins[addr];
  initial begin
    ins[0] = 8'h00;   // ADD [0]
    ins[1] = 8'h21;   // SUB [1]
    ins[2] = 8'h42;   // AND [2]
    ins[3] = 8'h63;   // OR  [3]
    ins[4] = 8'h84;   // NOT [4]
    ins[5] = 8'hA4;   // XOR [4]
    ins[6] = 8'hC4;   // XNOR[4]
    ins[7] = 8'hEA;   // JMP 10
    ins[10] = 8'h00;  // ADD [0]
    ins[11] = 8'hE0;  // JMP 0
  end
endmodule

module datapath(
  input         clk,
  input         rst,
  input         ld_ac,
  input         ac_src,
  input         pc_src,
  output [2:0]  op,
  output [4:0]  im_addr,
  input  [7:0]  im_in,
  output [4:0]  dm_addr,
  output [7:0]  dm_in,
  input  [7:0]  dm_out,
  output [7:0]  ac_out,
  output [7:0]  alu_out
);
  wire   [7:0]  mux2_out;
  wire   [4:0]  mux1_out;
  wire   [4:0]  adder_out;
  wire   [4:0]  pc_out;

  pc pc0(
    .clk(clk),
    .rst(rst),
    .in(mux1_out),
    .out(pc_out)
  );
  adder adder0(
    .a(pc_out),
    .b(5'b00001),
    .out(adder_out)
  );
  mux2to1#(.BITS(5)) mux1(
    .sel(pc_src),
    .in1(adder_out),
    .in2(im_in[4:0]),
    .out(mux1_out)
  );
  acc acc0(
    .clk(clk),
    .rst(rst),
    .ld(ld_ac),
    .in(mux2_out),
    .out(ac_out)
  );
  alu alu0(
    .op(op),
    .a(ac_out),
    .b(dm_out),
    .out(alu_out)
  );
  mux2to1#(.BITS(8)) mux2(
    .sel(ac_src),
    .in1(alu_out),
    .in2(dm_out),
    .out(mux2_out)
  );
  assign im_addr = pc_out;
  assign op = im_in[7:5];
  assign dm_addr = im_in[4:0];
  assign dm_in = ac_out;
endmodule

module CPU(
  input         clk,
  input         rst,
  output        rd_mem,
  output        wr_mem,
  output  [4:0] im_addr,
  output  [4:0] dm_addr,
  input   [7:0] im_in,
  output  [7:0] dm_in,
  input   [7:0] dm_out,
  output  [7:0] ac_out,
  output  [7:0] alu_out,
  output  [2:0] op
);
  wire ld_ac;
  wire ac_src;
  wire pc_src;
  wire branch;
  datapath dpu(
    .clk(clk),
    .rst(rst),
    .ld_ac(ld_ac),
    .ac_src(ac_src),
    .pc_src(pc_src),
    .op(op),
    .im_addr(im_addr),
    .dm_addr(dm_addr),
    .im_in(im_in),
    .dm_in(dm_in),
    .dm_out(dm_out),
    .ac_out(ac_out),
    .alu_out(alu_out)
  );
  controller ctl(
    .op(op),
    .rd_mem(rd_mem),
    .wr_mem(wr_mem),
    .ld_ac(ld_ac),
    .ac_src(ac_src),
    .pc_src(pc_src),
    .branch(branch)
  );
endmodule

tb/single_tb.v
// modified from https://www.slideshare.net/slideshow/8-bit-single-cycle-processor/30891706
module single_tb;
  initial begin
    $dumpfile("single_tb.vcd");
    $dumpvars(0, single_tb);
  end

  reg clk;
  reg rst;
  wire [7:0] im_in;
  wire [7:0] dm_out;
  // for inspection
  wire rd_mem;
  wire wr_mem;
  wire [4:0] im_addr;
  wire [4:0] dm_addr;
  wire [7:0] dm_in;
  wire [7:0] ac_out;
  wire [7:0] alu_out;
  wire [2:0] op;

  CPU cpu(
    .clk(clk),
    .rst(rst),
    .rd_mem(rd_mem),
    .wr_mem(wr_mem),
    .im_addr(im_addr),
    .dm_addr(dm_addr),
    .im_in(im_in),
    .dm_in(dm_in),
    .dm_out(dm_out),
    .ac_out(ac_out),
    .alu_out(alu_out),
    .op(op)
  );
  codemem im(
    .addr(im_addr), 
    .out(im_in)
  );
  datamem dm(
    .rd(rd_mem),
    .wr(wr_mem),
    .addr(dm_addr), 
    .in(dm_in), 
    .out(dm_out)
  );

  initial begin
    clk = 0;
    rst = 1;
    #20 rst = 0;
    #500 $finish;
  end
  always #10 clk = ~clk;
endmodule

single_tb.vcd
$date
	Mon Aug 05 17:07:50 2024
$end
$version
	Icarus Verilog
$end
$timescale
	1s
$end
$scope module single_tb $end
$var wire 1 ! wr_mem $end
$var wire 1 " rd_mem $end
$var wire 3 # op [2:0] $end
$var wire 8 $ im_in [7:0] $end
$var wire 5 % im_addr [4:0] $end
$var wire 8 & dm_out [7:0] $end
$var wire 8 ' dm_in [7:0] $end
$var wire 5 ( dm_addr [4:0] $end
$var wire 8 ) alu_out [7:0] $end
$var wire 8 * ac_out [7:0] $end
$var reg 1 + clk $end
$var reg 1 , rst $end
$scope module cpu $end
$var wire 1 + clk $end
$var wire 1 , rst $end
$var wire 1 ! wr_mem $end
$var wire 1 " rd_mem $end
$var wire 1 - pc_src $end
$var wire 3 . op [2:0] $end
$var wire 1 / ld_ac $end
$var wire 8 0 im_in [7:0] $end
$var wire 5 1 im_addr [4:0] $end
$var wire 8 2 dm_out [7:0] $end
$var wire 8 3 dm_in [7:0] $end
$var wire 5 4 dm_addr [4:0] $end
$var wire 1 5 branch $end
$var wire 8 6 alu_out [7:0] $end
$var wire 1 7 ac_src $end
$var wire 8 8 ac_out [7:0] $end
$scope module ctl $end
$var wire 3 9 op [2:0] $end
$var reg 1 7 ac_src $end
$var reg 1 5 branch $end
$var reg 1 / ld_ac $end
$var reg 1 - pc_src $end
$var reg 1 " rd_mem $end
$var reg 1 ! wr_mem $end
$upscope $end
$scope module dpu $end
$var wire 1 7 ac_src $end
$var wire 1 + clk $end
$var wire 8 : dm_in [7:0] $end
$var wire 5 ; im_addr [4:0] $end
$var wire 1 / ld_ac $end
$var wire 1 - pc_src $end
$var wire 1 , rst $end
$var wire 5 < pc_out [4:0] $end
$var wire 3 = op [2:0] $end
$var wire 8 > mux2_out [7:0] $end
$var wire 5 ? mux1_out [4:0] $end
$var wire 8 @ im_in [7:0] $end
$var wire 8 A dm_out [7:0] $end
$var wire 5 B dm_addr [4:0] $end
$var wire 8 C alu_out [7:0] $end
$var wire 5 D adder_out [4:0] $end
$var wire 8 E ac_out [7:0] $end
$scope module acc0 $end
$var wire 1 + clk $end
$var wire 1 / ld $end
$var wire 1 , rst $end
$var wire 8 F in [7:0] $end
$var reg 8 G out [7:0] $end
$upscope $end
$scope module adder0 $end
$var wire 5 H b [4:0] $end
$var wire 5 I out [4:0] $end
$var wire 5 J a [4:0] $end
$upscope $end
$scope module alu0 $end
$var wire 8 K a [7:0] $end
$var wire 3 L op [2:0] $end
$var wire 8 M b [7:0] $end
$var reg 8 N out [7:0] $end
$upscope $end
$scope module mux1 $end
$var wire 5 O in1 [4:0] $end
$var wire 5 P in2 [4:0] $end
$var wire 1 - sel $end
$var wire 5 Q out [4:0] $end
$var parameter 32 R BITS $end
$upscope $end
$scope module mux2 $end
$var wire 8 S in1 [7:0] $end
$var wire 1 7 sel $end
$var wire 8 T out [7:0] $end
$var wire 8 U in2 [7:0] $end
$var parameter 32 V BITS $end
$upscope $end
$scope module pc0 $end
$var wire 1 + clk $end
$var wire 5 W in [4:0] $end
$var wire 1 , rst $end
$var reg 5 X out [4:0] $end
$upscope $end
$upscope $end
$upscope $end
$scope module dm $end
$var wire 5 Y addr [4:0] $end
$var wire 8 Z in [7:0] $end
$var wire 1 " rd $end
$var wire 1 ! wr $end
$var reg 8 [ out [7:0] $end
$upscope $end
$scope module im $end
$var wire 5 \ addr [4:0] $end
$var reg 8 ] out [7:0] $end
$upscope $end
$upscope $end
$enddefinitions $end
$comment Show the parameter values. $end
$dumpall
b1000 V
b101 R
$end
#0
$dumpvars
bx ]
bx \
bx [
bx Z
bx Y
bx X
bx W
bx U
bx T
bx S
bx Q
bx P
bx O
bx N
bx M
bx L
bx K
bx J
bx I
b1 H
bx G
bx F
bx E
bx D
bx C
bx B
bx A
bx @
bx ?
bx >
bx =
bx <
bx ;
bx :
bx 9
bx 8
x7
bx 6
x5
bx 4
bx 3
bx 2
bx 1
bx 0
x/
bx .
x-
1,
0+
bx *
bx )
bx (
bx '
bx &
bx %
bx $
bx #
x"
x!
$end
#10
b1 >
b1 F
b1 T
b1 &
b1 2
b1 A
b1 M
b1 U
b1 [
05
0-
07
1/
0!
1"
b1 ?
b1 Q
b1 W
b0 (
b0 4
b0 B
b0 Y
b0 #
b0 .
b0 9
b0 =
b0 L
b0 P
b0 $
b0 0
b0 @
b0 ]
b1 D
b1 I
b1 O
b0 %
b0 1
b0 ;
b0 \
b0 <
b0 J
b0 X
b1 )
b1 6
b1 C
b1 N
b1 S
b0 '
b0 3
b0 :
b0 Z
b0 *
b0 8
b0 E
b0 G
b0 K
1+
#20
0+
0,
#30
b10 &
b10 2
b10 A
b10 M
b10 U
b10 [
1/
1"
b11111111 >
b11111111 F
b11111111 T
b1 (
b1 4
b1 B
b1 Y
b1 #
b1 .
b1 9
b1 =
b1 L
b1 P
b11111111 )
b11111111 6
b11111111 C
b11111111 N
b11111111 S
b10 ?
b10 Q
b10 W
b100001 $
b100001 0
b100001 @
b100001 ]
b1 '
b1 3
b1 :
b1 Z
b1 *
b1 8
b1 E
b1 G
b1 K
b10 D
b10 I
b10 O
b1 %
b1 1
b1 ;
b1 \
b1 <
b1 J
b1 X
1+
#40
0+
#50
b11 &
b11 2
b11 A
b11 M
b11 U
b11 [
1/
1"
b10 (
b10 4
b10 B
b10 Y
b10 #
b10 .
b10 9
b10 =
b10 L
b10 P
b11 >
b11 F
b11 T
b11 ?
b11 Q
b11 W
b1000010 $
b1000010 0
b1000010 @
b1000010 ]
b11 )
b11 6
b11 C
b11 N
b11 S
b11 D
b11 I
b11 O
b10 %
b10 1
b10 ;
b10 \
b10 <
b10 J
b10 X
b11111111 '
b11111111 3
b11111111 :
b11111111 Z
b11111111 *
b11111111 8
b11111111 E
b11111111 G
b11111111 K
1+
#60
0+
#70
b111 >
b111 F
b111 T
b111 )
b111 6
b111 C
b111 N
b111 S
b100 &
b100 2
b100 A
b100 M
b100 U
b100 [
1/
1"
b11 (
b11 4
b11 B
b11 Y
b11 #
b11 .
b11 9
b11 =
b11 L
b11 P
b100 ?
b100 Q
b100 W
b1100011 $
b1100011 0
b1100011 @
b1100011 ]
b11 '
b11 3
b11 :
b11 Z
b11 *
b11 8
b11 E
b11 G
b11 K
b100 D
b100 I
b100 O
b11 %
b11 1
b11 ;
b11 \
b11 <
b11 J
b11 X
1+
#80
0+
#90
b11111010 >
b11111010 F
b11111010 T
b101 &
b101 2
b101 A
b101 M
b101 U
b101 [
1/
1"
b11111010 )
b11111010 6
b11111010 C
b11111010 N
b11111010 S
b100 (
b100 4
b100 B
b100 Y
b100 #
b100 .
b100 9
b100 =
b100 L
b100 P
b101 ?
b101 Q
b101 W
b10000100 $
b10000100 0
b10000100 @
b10000100 ]
b101 D
b101 I
b101 O
b100 %
b100 1
b100 ;
b100 \
b100 <
b100 J
b100 X
b111 '
b111 3
b111 :
b111 Z
b111 *
b111 8
b111 E
b111 G
b111 K
1+
#100
0+
#110
b11111111 >
b11111111 F
b11111111 T
1/
1"
b11111111 )
b11111111 6
b11111111 C
b11111111 N
b11111111 S
b101 #
b101 .
b101 9
b101 =
b101 L
b110 ?
b110 Q
b110 W
b10100100 $
b10100100 0
b10100100 @
b10100100 ]
b11111010 '
b11111010 3
b11111010 :
b11111010 Z
b11111010 *
b11111010 8
b11111010 E
b11111010 G
b11111010 K
b110 D
b110 I
b110 O
b101 %
b101 1
b101 ;
b101 \
b101 <
b101 J
b101 X
1+
#120
0+
#130
1/
1"
b110 #
b110 .
b110 9
b110 =
b110 L
b101 >
b101 F
b101 T
b111 ?
b111 Q
b111 W
b11000100 $
b11000100 0
b11000100 @
b11000100 ]
b101 )
b101 6
b101 C
b101 N
b101 S
b111 D
b111 I
b111 O
b110 %
b110 1
b110 ;
b110 \
b110 <
b110 J
b110 X
b11111111 '
b11111111 3
b11111111 :
b11111111 Z
b11111111 *
b11111111 8
b11111111 E
b11111111 G
b11111111 K
1+
#140
0+
#150
15
1-
0/
0"
b0 >
b0 F
b0 T
b1010 (
b1010 4
b1010 B
b1010 Y
b111 #
b111 .
b111 9
b111 =
b111 L
b1010 P
b0 )
b0 6
b0 C
b0 N
b0 S
b1010 ?
b1010 Q
b1010 W
b11101010 $
b11101010 0
b11101010 @
b11101010 ]
b101 '
b101 3
b101 :
b101 Z
b101 *
b101 8
b101 E
b101 G
b101 K
b1000 D
b1000 I
b1000 O
b111 %
b111 1
b111 ;
b111 \
b111 <
b111 J
b111 X
1+
#160
0+
#170
b110 >
b110 F
b110 T
b1 &
b1 2
b1 A
b1 M
b1 U
b1 [
1/
1"
05
0-
b110 )
b110 6
b110 C
b110 N
b110 S
b1011 ?
b1011 Q
b1011 W
b0 (
b0 4
b0 B
b0 Y
b0 #
b0 .
b0 9
b0 =
b0 L
b0 P
b0 $
b0 0
b0 @
b0 ]
b1011 D
b1011 I
b1011 O
b1010 %
b1010 1
b1010 ;
b1010 \
b1010 <
b1010 J
b1010 X
1+
#180
0+
#190
15
1-
0/
0"
b0 >
b0 F
b0 T
b111 #
b111 .
b111 9
b111 =
b111 L
b0 )
b0 6
b0 C
b0 N
b0 S
b0 ?
b0 Q
b0 W
b11100000 $
b11100000 0
b11100000 @
b11100000 ]
b110 '
b110 3
b110 :
b110 Z
b110 *
b110 8
b110 E
b110 G
b110 K
b1100 D
b1100 I
b1100 O
b1011 %
b1011 1
b1011 ;
b1011 \
b1011 <
b1011 J
b1011 X
1+
#200
0+
#210
b1 ?
b1 Q
b1 W
b111 >
b111 F
b111 T
1/
1"
05
0-
b111 )
b111 6
b111 C
b111 N
b111 S
b0 #
b0 .
b0 9
b0 =
b0 L
b0 $
b0 0
b0 @
b0 ]
b1 D
b1 I
b1 O
b0 %
b0 1
b0 ;
b0 \
b0 <
b0 J
b0 X
1+
#220
0+
#230
b10 &
b10 2
b10 A
b10 M
b10 U
b10 [
1/
1"
b101 >
b101 F
b101 T
b1 (
b1 4
b1 B
b1 Y
b1 #
b1 .
b1 9
b1 =
b1 L
b1 P
b101 )
b101 6
b101 C
b101 N
b101 S
b10 ?
b10 Q
b10 W
b100001 $
b100001 0
b100001 @
b100001 ]
b111 '
b111 3
b111 :
b111 Z
b111 *
b111 8
b111 E
b111 G
b111 K
b10 D
b10 I
b10 O
b1 %
b1 1
b1 ;
b1 \
b1 <
b1 J
b1 X
1+
#240
0+
#250
b11 &
b11 2
b11 A
b11 M
b11 U
b11 [
1/
1"
b10 (
b10 4
b10 B
b10 Y
b10 #
b10 .
b10 9
b10 =
b10 L
b10 P
b1 >
b1 F
b1 T
b11 ?
b11 Q
b11 W
b1000010 $
b1000010 0
b1000010 @
b1000010 ]
b1 )
b1 6
b1 C
b1 N
b1 S
b11 D
b11 I
b11 O
b10 %
b10 1
b10 ;
b10 \
b10 <
b10 J
b10 X
b101 '
b101 3
b101 :
b101 Z
b101 *
b101 8
b101 E
b101 G
b101 K
1+
#260
0+
#270
b101 >
b101 F
b101 T
b100 &
b100 2
b100 A
b100 M
b100 U
b100 [
1/
1"
b101 )
b101 6
b101 C
b101 N
b101 S
b11 (
b11 4
b11 B
b11 Y
b11 #
b11 .
b11 9
b11 =
b11 L
b11 P
b100 ?
b100 Q
b100 W
b1100011 $
b1100011 0
b1100011 @
b1100011 ]
b1 '
b1 3
b1 :
b1 Z
b1 *
b1 8
b1 E
b1 G
b1 K
b100 D
b100 I
b100 O
b11 %
b11 1
b11 ;
b11 \
b11 <
b11 J
b11 X
1+
#280
0+
#290
b11111010 >
b11111010 F
b11111010 T
b101 &
b101 2
b101 A
b101 M
b101 U
b101 [
1/
1"
b11111010 )
b11111010 6
b11111010 C
b11111010 N
b11111010 S
b100 (
b100 4
b100 B
b100 Y
b100 #
b100 .
b100 9
b100 =
b100 L
b100 P
b101 ?
b101 Q
b101 W
b10000100 $
b10000100 0
b10000100 @
b10000100 ]
b101 D
b101 I
b101 O
b100 %
b100 1
b100 ;
b100 \
b100 <
b100 J
b100 X
b101 '
b101 3
b101 :
b101 Z
b101 *
b101 8
b101 E
b101 G
b101 K
1+
#300
0+
#310
b11111111 >
b11111111 F
b11111111 T
1/
1"
b11111111 )
b11111111 6
b11111111 C
b11111111 N
b11111111 S
b101 #
b101 .
b101 9
b101 =
b101 L
b110 ?
b110 Q
b110 W
b10100100 $
b10100100 0
b10100100 @
b10100100 ]
b11111010 '
b11111010 3
b11111010 :
b11111010 Z
b11111010 *
b11111010 8
b11111010 E
b11111010 G
b11111010 K
b110 D
b110 I
b110 O
b101 %
b101 1
b101 ;
b101 \
b101 <
b101 J
b101 X
1+
#320
0+
#330
1/
1"
b110 #
b110 .
b110 9
b110 =
b110 L
b101 >
b101 F
b101 T
b111 ?
b111 Q
b111 W
b11000100 $
b11000100 0
b11000100 @
b11000100 ]
b101 )
b101 6
b101 C
b101 N
b101 S
b111 D
b111 I
b111 O
b110 %
b110 1
b110 ;
b110 \
b110 <
b110 J
b110 X
b11111111 '
b11111111 3
b11111111 :
b11111111 Z
b11111111 *
b11111111 8
b11111111 E
b11111111 G
b11111111 K
1+
#340
0+
#350
15
1-
0/
0"
b0 >
b0 F
b0 T
b1010 (
b1010 4
b1010 B
b1010 Y
b111 #
b111 .
b111 9
b111 =
b111 L
b1010 P
b0 )
b0 6
b0 C
b0 N
b0 S
b1010 ?
b1010 Q
b1010 W
b11101010 $
b11101010 0
b11101010 @
b11101010 ]
b101 '
b101 3
b101 :
b101 Z
b101 *
b101 8
b101 E
b101 G
b101 K
b1000 D
b1000 I
b1000 O
b111 %
b111 1
b111 ;
b111 \
b111 <
b111 J
b111 X
1+
#360
0+
#370
b110 >
b110 F
b110 T
b1 &
b1 2
b1 A
b1 M
b1 U
b1 [
1/
1"
05
0-
b110 )
b110 6
b110 C
b110 N
b110 S
b1011 ?
b1011 Q
b1011 W
b0 (
b0 4
b0 B
b0 Y
b0 #
b0 .
b0 9
b0 =
b0 L
b0 P
b0 $
b0 0
b0 @
b0 ]
b1011 D
b1011 I
b1011 O
b1010 %
b1010 1
b1010 ;
b1010 \
b1010 <
b1010 J
b1010 X
1+
#380
0+
#390
15
1-
0/
0"
b0 >
b0 F
b0 T
b111 #
b111 .
b111 9
b111 =
b111 L
b0 )
b0 6
b0 C
b0 N
b0 S
b0 ?
b0 Q
b0 W
b11100000 $
b11100000 0
b11100000 @
b11100000 ]
b110 '
b110 3
b110 :
b110 Z
b110 *
b110 8
b110 E
b110 G
b110 K
b1100 D
b1100 I
b1100 O
b1011 %
b1011 1
b1011 ;
b1011 \
b1011 <
b1011 J
b1011 X
1+
#400
0+
#410
b1 ?
b1 Q
b1 W
b111 >
b111 F
b111 T
1/
1"
05
0-
b111 )
b111 6
b111 C
b111 N
b111 S
b0 #
b0 .
b0 9
b0 =
b0 L
b0 $
b0 0
b0 @
b0 ]
b1 D
b1 I
b1 O
b0 %
b0 1
b0 ;
b0 \
b0 <
b0 J
b0 X
1+
#420
0+
#430
b10 &
b10 2
b10 A
b10 M
b10 U
b10 [
1/
1"
b101 >
b101 F
b101 T
b1 (
b1 4
b1 B
b1 Y
b1 #
b1 .
b1 9
b1 =
b1 L
b1 P
b101 )
b101 6
b101 C
b101 N
b101 S
b10 ?
b10 Q
b10 W
b100001 $
b100001 0
b100001 @
b100001 ]
b111 '
b111 3
b111 :
b111 Z
b111 *
b111 8
b111 E
b111 G
b111 K
b10 D
b10 I
b10 O
b1 %
b1 1
b1 ;
b1 \
b1 <
b1 J
b1 X
1+
#440
0+
#450
b11 &
b11 2
b11 A
b11 M
b11 U
b11 [
1/
1"
b10 (
b10 4
b10 B
b10 Y
b10 #
b10 .
b10 9
b10 =
b10 L
b10 P
b1 >
b1 F
b1 T
b11 ?
b11 Q
b11 W
b1000010 $
b1000010 0
b1000010 @
b1000010 ]
b1 )
b1 6
b1 C
b1 N
b1 S
b11 D
b11 I
b11 O
b10 %
b10 1
b10 ;
b10 \
b10 <
b10 J
b10 X
b101 '
b101 3
b101 :
b101 Z
b101 *
b101 8
b101 E
b101 G
b101 K
1+
#460
0+
#470
b101 >
b101 F
b101 T
b100 &
b100 2
b100 A
b100 M
b100 U
b100 [
1/
1"
b101 )
b101 6
b101 C
b101 N
b101 S
b11 (
b11 4
b11 B
b11 Y
b11 #
b11 .
b11 9
b11 =
b11 L
b11 P
b100 ?
b100 Q
b100 W
b1100011 $
b1100011 0
b1100011 @
b1100011 ]
b1 '
b1 3
b1 :
b1 Z
b1 *
b1 8
b1 E
b1 G
b1 K
b100 D
b100 I
b100 O
b11 %
b11 1
b11 ;
b11 \
b11 <
b11 J
b11 X
1+
#480
0+
#490
b11111010 >
b11111010 F
b11111010 T
b101 &
b101 2
b101 A
b101 M
b101 U
b101 [
1/
1"
b11111010 )
b11111010 6
b11111010 C
b11111010 N
b11111010 S
b100 (
b100 4
b100 B
b100 Y
b100 #
b100 .
b100 9
b100 =
b100 L
b100 P
b101 ?
b101 Q
b101 W
b10000100 $
b10000100 0
b10000100 @
b10000100 ]
b101 D
b101 I
b101 O
b100 %
b100 1
b100 ;
b100 \
b100 <
b100 J
b100 X
b101 '
b101 3
b101 :
b101 Z
b101 *
b101 8
b101 E
b101 G
b101 K
1+
#500
0+
#510
b11111111 >
b11111111 F
b11111111 T
1/
1"
b11111111 )
b11111111 6
b11111111 C
b11111111 N
b11111111 S
b101 #
b101 .
b101 9
b101 =
b101 L
b110 ?
b110 Q
b110 W
b10100100 $
b10100100 0
b10100100 @
b10100100 ]
b11111010 '
b11111010 3
b11111010 :
b11111010 Z
b11111010 *
b11111010 8
b11111010 E
b11111010 G
b11111010 K
b110 D
b110 I
b110 O
b101 %
b101 1
b101 ;
b101 \
b101 <
b101 J
b101 X
1+
